skkda/__init__.py
skkda/base.py
tests/__init__.py
tests/test_base.py
scikit_kda-0.1.1.dist-info/LICENSE
scikit_kda-0.1.1.dist-info/METADATA
scikit_kda-0.1.1.dist-info/WHEEL
scikit_kda-0.1.1.dist-info/top_level.txt
scikit_kda-0.1.1.dist-info/RECORD
