Metadata-Version: 2.1
Name: scikit-kda
Version: 0.1.1
Summary: Scikit-learn-compatible Kernel Discriminant Analysis
Home-page: https://github.com/daviddiazvico/scikit-kda
Author: David Diaz Vico
Author-email: david.diaz.vico@outlook.com
License: UNKNOWN
Download-URL: https://github.com/daviddiazvico/scikit-kda/archive/v0.1.1.tar.gz
Keywords: scikit-learn,kda
Platform: UNKNOWN
Classifier: Intended Audience :: Science/Research
Classifier: Topic :: Scientific/Engineering
Classifier: Programming Language :: Python
Classifier: Programming Language :: Python :: 3
Classifier: Programming Language :: Python :: 3.6
Requires-Dist: scikit-learn
